emoney/__init__.py
emoneyge_py-1.0.1.dist-info/LICENSE
emoneyge_py-1.0.1.dist-info/METADATA
emoneyge_py-1.0.1.dist-info/WHEEL
emoneyge_py-1.0.1.dist-info/top_level.txt
emoneyge_py-1.0.1.dist-info/RECORD
