Metadata-Version: 2.1
Name: emoneyge-py
Version: 1.0.1
Summary: Unofficial Python library for emoney.ge automation
Home-page: https://github.com/Phalelashvili/emoneyge-py
Author: Spartak Phalelashvili
Author-email: phalelashvili@protonmail.com
License: MIT
Download-URL: https://github.com/Phalelashvili/emoneyge-py/tarball/1.0.1
Keywords: emoney.ge,emoney,emoneyy,emoneygepy,emoneyge-py,emoney.ge automation,emoney automation
Platform: UNKNOWN
Requires-Dist: beautifulsoup4
Requires-Dist: requests
